Compiled from "FinalClient.java"
public final class com.yehao.boot.search.client.FinalClient {
  public static void main(java.lang.String[]);
    Code:
       0: new           #1                  // class com/yehao/boot/search/client/FinalClient
       3: dup
       4: invokespecial #2                  // Method "<init>":()V
       7: astore_1
       8: getstatic     #3                  // Field java/lang/System.out:Ljava/io/PrintStream;
      11: aload_1
      12: invokevirtual #4                  // Method toString:()Ljava/lang/String;
      15: invokevirtual #5                  // Method java/io/PrintStream.println:(Ljava/lang/String;)V
      18: return
    LineNumberTable:
      line 19: 0
      line 20: 8
      line 21: 18
    LocalVariableTable:
      Start  Length  Slot  Name   Signature
          0      19     0  args   [Ljava/lang/String;
          8      11     1 finalClient   Lcom/yehao/boot/search/client/FinalClient;

  public com.yehao.boot.search.client.FinalClient();
    Code:
       0: aload_0
       1: invokespecial #6                  // Method java/lang/Object."<init>":()V
       4: aload_0
       5: aload_0
       6: invokevirtual #7                  // Method getClassName:()Ljava/lang/String;
       9: putfield      #8                  // Field className:Ljava/lang/String;
      12: return
    LineNumberTable:
      line 11: 0
      line 15: 4
    LocalVariableTable:
      Start  Length  Slot  Name   Signature
          0      13     0  this   Lcom/yehao/boot/search/client/FinalClient;

  public java.lang.String getName();
    Code:
       0: aload_0
       1: getfield      #9                  // Field name:Ljava/lang/String;
       4: areturn
    LineNumberTable:
      line 13: 0
    LocalVariableTable:
      Start  Length  Slot  Name   Signature
          0       5     0  this   Lcom/yehao/boot/search/client/FinalClient;

  public java.lang.Integer getValue();
    Code:
       0: aload_0
       1: getfield      #10                 // Field value:Ljava/lang/Integer;
       4: areturn
    LineNumberTable:
      line 14: 0
    LocalVariableTable:
      Start  Length  Slot  Name   Signature
          0       5     0  this   Lcom/yehao/boot/search/client/FinalClient;

  public java.lang.String getClassName();
    Code:
       0: aload_0
       1: getfield      #8                  // Field className:Ljava/lang/String;
       4: areturn
    LineNumberTable:
      line 15: 0
    LocalVariableTable:
      Start  Length  Slot  Name   Signature
          0       5     0  this   Lcom/yehao/boot/search/client/FinalClient;

  public void setName(java.lang.String);
    Code:
       0: aload_0
       1: aload_1
       2: putfield      #9                  // Field name:Ljava/lang/String;
       5: return
    LineNumberTable:
      line 11: 0
    LocalVariableTable:
      Start  Length  Slot  Name   Signature
          0       6     0  this   Lcom/yehao/boot/search/client/FinalClient;
          0       6     1  name   Ljava/lang/String;

  public void setValue(java.lang.Integer);
    Code:
       0: aload_0
       1: aload_1
       2: putfield      #10                 // Field value:Ljava/lang/Integer;
       5: return
    LineNumberTable:
      line 11: 0
    LocalVariableTable:
      Start  Length  Slot  Name   Signature
          0       6     0  this   Lcom/yehao/boot/search/client/FinalClient;
          0       6     1 value   Ljava/lang/Integer;

  public boolean equals(java.lang.Object);
    Code:
       0: aload_1
       1: aload_0
       2: if_acmpne     7
       5: iconst_1
       6: ireturn
       7: aload_1
       8: instanceof    #1                  // class com/yehao/boot/search/client/FinalClient
      11: ifne          16
      14: iconst_0
      15: ireturn
      16: aload_1
      17: checkcast     #1                  // class com/yehao/boot/search/client/FinalClient
      20: astore_2
      21: aload_0
      22: invokevirtual #11                 // Method getName:()Ljava/lang/String;
      25: astore_3
      26: aload_2
      27: invokevirtual #11                 // Method getName:()Ljava/lang/String;
      30: astore        4
      32: aload_3
      33: ifnonnull     44
      36: aload         4
      38: ifnull        55
      41: goto          53
      44: aload_3
      45: aload         4
      47: invokevirtual #12                 // Method java/lang/Object.equals:(Ljava/lang/Object;)Z
      50: ifne          55
      53: iconst_0
      54: ireturn
      55: aload_0
      56: invokevirtual #13                 // Method getValue:()Ljava/lang/Integer;
      59: astore        5
      61: aload_2
      62: invokevirtual #13                 // Method getValue:()Ljava/lang/Integer;
      65: astore        6
      67: aload         5
      69: ifnonnull     80
      72: aload         6
      74: ifnull        92
      77: goto          90
      80: aload         5
      82: aload         6
      84: invokevirtual #12                 // Method java/lang/Object.equals:(Ljava/lang/Object;)Z
      87: ifne          92
      90: iconst_0
      91: ireturn
      92: aload_0
      93: invokevirtual #7                  // Method getClassName:()Ljava/lang/String;
      96: astore        7
      98: aload_2
      99: invokevirtual #7                  // Method getClassName:()Ljava/lang/String;
     102: astore        8
     104: aload         7
     106: ifnonnull     117
     109: aload         8
     111: ifnull        129
     114: goto          127
     117: aload         7
     119: aload         8
     121: invokevirtual #12                 // Method java/lang/Object.equals:(Ljava/lang/Object;)Z
     124: ifne          129
     127: iconst_0
     128: ireturn
     129: iconst_1
     130: ireturn
    LineNumberTable:
      line 11: 0
    LocalVariableTable:
      Start  Length  Slot  Name   Signature
          0     131     0  this   Lcom/yehao/boot/search/client/FinalClient;
          0     131     1     o   Ljava/lang/Object;
         21     110     2 other   Lcom/yehao/boot/search/client/FinalClient;
         26     105     3 this$name   Ljava/lang/Object;
         32      99     4 other$name   Ljava/lang/Object;
         61      70     5 this$value   Ljava/lang/Object;
         67      64     6 other$value   Ljava/lang/Object;
         98      33     7 this$className   Ljava/lang/Object;
        104      27     8 other$className   Ljava/lang/Object;

  public int hashCode();
    Code:
       0: bipush        59
       2: istore_1
       3: iconst_1
       4: istore_2
       5: aload_0
       6: invokevirtual #11                 // Method getName:()Ljava/lang/String;
       9: astore_3
      10: iload_2
      11: bipush        59
      13: imul
      14: aload_3
      15: ifnonnull     23
      18: bipush        43
      20: goto          27
      23: aload_3
      24: invokevirtual #14                 // Method java/lang/Object.hashCode:()I
      27: iadd
      28: istore_2
      29: aload_0
      30: invokevirtual #13                 // Method getValue:()Ljava/lang/Integer;
      33: astore        4
      35: iload_2
      36: bipush        59
      38: imul
      39: aload         4
      41: ifnonnull     49
      44: bipush        43
      46: goto          54
      49: aload         4
      51: invokevirtual #14                 // Method java/lang/Object.hashCode:()I
      54: iadd
      55: istore_2
      56: aload_0
      57: invokevirtual #7                  // Method getClassName:()Ljava/lang/String;
      60: astore        5
      62: iload_2
      63: bipush        59
      65: imul
      66: aload         5
      68: ifnonnull     76
      71: bipush        43
      73: goto          81
      76: aload         5
      78: invokevirtual #14                 // Method java/lang/Object.hashCode:()I
      81: iadd
      82: istore_2
      83: iload_2
      84: ireturn
    LineNumberTable:
      line 11: 0
    LocalVariableTable:
      Start  Length  Slot  Name   Signature
          0      85     0  this   Lcom/yehao/boot/search/client/FinalClient;
          3      82     1 PRIME   I
          5      80     2 result   I
         10      75     3 $name   Ljava/lang/Object;
         35      50     4 $value   Ljava/lang/Object;
         62      23     5 $className   Ljava/lang/Object;

  public java.lang.String toString();
    Code:
       0: new           #15                 // class java/lang/StringBuilder
       3: dup
       4: invokespecial #16                 // Method java/lang/StringBuilder."<init>":()V
       7: ldc           #17                 // String FinalClient(name=
       9: invokevirtual #18                 // Method java/lang/StringBuilder.append:(Ljava/lang/String;)Ljava/lang/StringBuilder;
      12: aload_0
      13: invokevirtual #11                 // Method getName:()Ljava/lang/String;
      16: invokevirtual #18                 // Method java/lang/StringBuilder.append:(Ljava/lang/String;)Ljava/lang/StringBuilder;
      19: ldc           #19                 // String , value=
      21: invokevirtual #18                 // Method java/lang/StringBuilder.append:(Ljava/lang/String;)Ljava/lang/StringBuilder;
      24: aload_0
      25: invokevirtual #13                 // Method getValue:()Ljava/lang/Integer;
      28: invokevirtual #20                 // Method java/lang/StringBuilder.append:(Ljava/lang/Object;)Ljava/lang/StringBuilder;
      31: ldc           #21                 // String , className=
      33: invokevirtual #18                 // Method java/lang/StringBuilder.append:(Ljava/lang/String;)Ljava/lang/StringBuilder;
      36: aload_0
      37: invokevirtual #7                  // Method getClassName:()Ljava/lang/String;
      40: invokevirtual #18                 // Method java/lang/StringBuilder.append:(Ljava/lang/String;)Ljava/lang/StringBuilder;
      43: ldc           #22                 // String )
      45: invokevirtual #18                 // Method java/lang/StringBuilder.append:(Ljava/lang/String;)Ljava/lang/StringBuilder;
      48: invokevirtual #23                 // Method java/lang/StringBuilder.toString:()Ljava/lang/String;
      51: areturn
    LineNumberTable:
      line 11: 0
    LocalVariableTable:
      Start  Length  Slot  Name   Signature
          0      52     0  this   Lcom/yehao/boot/search/client/FinalClient;
}
